{
	"@type":"Hierarchy",
	"Name":"DOMAIN",
	"Elements":
	[
		{
			"Name":"TOTAL_DOMAIN",
			"Type":"Consolidated"
		},
		{
			"Name":"ANGO",
			"Type":"Numeric"
		},
		{
			"Name":"AUST",
			"Type":"Numeric"
		},
		{
			"Name":"BORD",
			"Type":"Numeric"
		},
		{
			"Name":"BRAZ",
			"Type":"Numeric"
		},
		{
			"Name":"HONG",
			"Type":"Numeric"
		},
		{
			"Name":"MADR",
			"Type":"Numeric"
		},
		{
			"Name":"OSKA",
			"Type":"Numeric"
		},
		{
			"Name":"RASK",
			"Type":"Numeric"
		},
		{
			"Name":"SING",
			"Type":"Numeric"
		},
		{
			"Name":"SOUT",
			"Type":"Numeric"
		},
		{
			"Name":"VALD",
			"Type":"Numeric"
		},
		{
			"Name":"ZHUH",
			"Type":"Numeric"
		}
	],
	"Edges":
	[
		{
			"ParentName":"TOTAL_DOMAIN",
			"ComponentName":"ANGO",
			"Weight":1
		},
		{
			"ParentName":"TOTAL_DOMAIN",
			"ComponentName":"AUST",
			"Weight":1
		},
		{
			"ParentName":"TOTAL_DOMAIN",
			"ComponentName":"BORD",
			"Weight":1
		},
		{
			"ParentName":"TOTAL_DOMAIN",
			"ComponentName":"BRAZ",
			"Weight":1
		},
		{
			"ParentName":"TOTAL_DOMAIN",
			"ComponentName":"HONG",
			"Weight":1
		},
		{
			"ParentName":"TOTAL_DOMAIN",
			"ComponentName":"MADR",
			"Weight":1
		},
		{
			"ParentName":"TOTAL_DOMAIN",
			"ComponentName":"OSKA",
			"Weight":1
		},
		{
			"ParentName":"TOTAL_DOMAIN",
			"ComponentName":"RASK",
			"Weight":1
		},
		{
			"ParentName":"TOTAL_DOMAIN",
			"ComponentName":"SING",
			"Weight":1
		},
		{
			"ParentName":"TOTAL_DOMAIN",
			"ComponentName":"SOUT",
			"Weight":1
		},
		{
			"ParentName":"TOTAL_DOMAIN",
			"ComponentName":"VALD",
			"Weight":1
		},
		{
			"ParentName":"TOTAL_DOMAIN",
			"ComponentName":"ZHUH",
			"Weight":1
		}
	],
	"Subsets@Code.links":
	[
		"DOMAIN.subsets/Level0.json",
		"DOMAIN.subsets/tout.json"
	]
}